MANIFEST.in
README.rst
setup.py
aio/__init__.py
aio.app.egg-info/PKG-INFO
aio.app.egg-info/SOURCES.txt
aio.app.egg-info/dependency_links.txt
aio.app.egg-info/entry_points.txt
aio.app.egg-info/namespace_packages.txt
aio.app.egg-info/not-zip-safe
aio.app.egg-info/requires.txt
aio.app.egg-info/top_level.txt
aio/app/README.rst
aio/app/__init__.py
aio/app/aio.conf
aio/app/cmd.py
aio/app/logging.py
aio/app/management.py
aio/app/runner.py
aio/app/schedule.py
aio/app/server.py
aio/app/signal.py
aio/app/testing/__init__.py
aio/app/testing/cmd.py
aio/app/tests/__init__.py
aio/app/tests/test_cmd_run.py
aio/app/tests/test_run_listeners.py
aio/app/tests/test_run_schedulers.py
aio/app/tests/test_run_servers.py
aio/app/tests/test_runner.py
aio/app/tests/resources/__init__.py
aio/app/tests/resources/app.py
aio/app/tests/resources/test-1.conf
aio/app/tests/resources/test-2.conf